misc_tooling/__init__.py
misc_tooling/file_tools.py
misc_tooling/string_builder.py
misc_tooling-0.1.0.dist-info/METADATA
misc_tooling-0.1.0.dist-info/WHEEL
misc_tooling-0.1.0.dist-info/RECORD
