Metadata-Version: 2.3
Name: misc-tooling
Version: 0.1.0
Summary: 
Author: Bradley Allen
Author-email: 103772876+NocturnalLament@users.noreply.github.com
Requires-Python: >=3.13
Classifier: Programming Language :: Python :: 3
Classifier: Programming Language :: Python :: 3.13
Requires-Dist: requests (>=2.32.5,<3.0.0)
